dircol/__init__.py
dircol/core.py
dircol-0.1.0.dist-info/LICENSE
dircol-0.1.0.dist-info/METADATA
dircol-0.1.0.dist-info/WHEEL
dircol-0.1.0.dist-info/top_level.txt
dircol-0.1.0.dist-info/RECORD
