Metadata-Version: 2.1
Name: dircol
Version: 0.1.0
Summary: Pretty column-formatted and color-coded dir() output using Rich.
Author-email: Pritam Karmokar <pritam.karmokar@gmail.com>
License: MIT
Project-URL: Homepage, https://github.com/pritamKarmokar/dircol
Requires-Python: >=3.7
License-File: LICENSE
Requires-Dist: rich
